setup.cfg
setup.py
Please_Clap.egg-info/PKG-INFO
Please_Clap.egg-info/SOURCES.txt
Please_Clap.egg-info/dependency_links.txt
Please_Clap.egg-info/not-zip-safe
Please_Clap.egg-info/requires.txt
Please_Clap.egg-info/top_level.txt
bin/please-clap
please_clap/__init__.py
please_clap/applause_1.wav
please_clap.egg-info/PKG-INFO
please_clap.egg-info/SOURCES.txt
please_clap.egg-info/dependency_links.txt
please_clap.egg-info/not-zip-safe
please_clap.egg-info/requires.txt
please_clap.egg-info/top_level.txt