Metadata-Version: 1.0
Name: please-clap
Version: 0.1.0
Summary: A Python Module to help through those tough times
Home-page: http://github.com/raymondberg/please_clap
Author: Raymond Berg
Author-email: dev@raymondberg.com
License: MIT
Platform: UNKNOWN
